ShanYuObjectiveCBianchengYishu/README.md
ShanYuObjectiveCBianchengYishu/__init__.py
ShanYuObjectiveCBianchengYishu/__main__.py
ShanYuObjectiveCBianchengYishu/file.epub
ShanYuObjectiveCBianchengYishu/index.html
ShanYuObjectiveCBianchengYishu/css/__init__.py
ShanYuObjectiveCBianchengYishu/css/annotations.css
ShanYuObjectiveCBianchengYishu/css/main.css
ShanYuObjectiveCBianchengYishu/css/normalize.css
ShanYuObjectiveCBianchengYishu/css/popup.css
ShanYuObjectiveCBianchengYishu/font/__init__.py
ShanYuObjectiveCBianchengYishu/font/fontello.eot
ShanYuObjectiveCBianchengYishu/font/fontello.svg
ShanYuObjectiveCBianchengYishu/font/fontello.ttf
ShanYuObjectiveCBianchengYishu/font/fontello.woff
ShanYuObjectiveCBianchengYishu/img/__init__.py
ShanYuObjectiveCBianchengYishu/img/annotator-glyph-sprite.png
ShanYuObjectiveCBianchengYishu/img/annotator-icon-sprite.png
ShanYuObjectiveCBianchengYishu/img/apple-touch-icon.png
ShanYuObjectiveCBianchengYishu/img/cancelfullscreen.png
ShanYuObjectiveCBianchengYishu/img/close.png
ShanYuObjectiveCBianchengYishu/img/fullscreen.png
ShanYuObjectiveCBianchengYishu/img/loader.gif
ShanYuObjectiveCBianchengYishu/img/menu-icon.png
ShanYuObjectiveCBianchengYishu/img/save.png
ShanYuObjectiveCBianchengYishu/img/saved.png
ShanYuObjectiveCBianchengYishu/img/settings-s.png
ShanYuObjectiveCBianchengYishu/img/settings.png
ShanYuObjectiveCBianchengYishu/img/star.png
ShanYuObjectiveCBianchengYishu/js/__init__.py
ShanYuObjectiveCBianchengYishu/js/epub.js
ShanYuObjectiveCBianchengYishu/js/epub.min.js
ShanYuObjectiveCBianchengYishu/js/epub.min.map
ShanYuObjectiveCBianchengYishu/js/hooks.min.js
ShanYuObjectiveCBianchengYishu/js/hooks.min.map
ShanYuObjectiveCBianchengYishu/js/reader.js
ShanYuObjectiveCBianchengYishu/js/reader.js.map
ShanYuObjectiveCBianchengYishu/js/reader.min.js
ShanYuObjectiveCBianchengYishu/js/reader.min.map
ShanYuObjectiveCBianchengYishu/js/hooks/__init__.py
ShanYuObjectiveCBianchengYishu/js/hooks/extensions/__init__.py
shan_yu_objective_c_biancheng_yishu-2024.3.3.0.dist-info/METADATA
shan_yu_objective_c_biancheng_yishu-2024.3.3.0.dist-info/WHEEL
shan_yu_objective_c_biancheng_yishu-2024.3.3.0.dist-info/entry_points.txt
shan_yu_objective_c_biancheng_yishu-2024.3.3.0.dist-info/top_level.txt
shan_yu_objective_c_biancheng_yishu-2024.3.3.0.dist-info/RECORD
